{
    "dimension": 2,
    "variables": [
        "Eta",
        "Pt"
    ],
    "error_type": "absolute",
    "binning": {
        "x": [
            -2.5,
            2.5
        ],
        "y": [
            0.16,
            0.18,
            0.2,
            0.22,
            0.24,
            0.26,
            0.28,
            0.3,
            0.32,
            0.34,
            0.36,
            0.38,
            0.4,
            0.42,
            0.44,
            0.48,
            0.5,
            0.52,
            0.54,
            0.56,
            0.58,
            0.6,
            0.62,
            0.7000000000000001,
            0.74,
            0.76,
            0.9
        ]
    },
    "data": [
        {
            "bin": [
                -2.5,
                2.5
            ],
            "values": [
                {
                    "bin": [
                        0.16,
                        0.18
                    ],
                    "value": 0.01931653466802287,
                    "error_low": 0.030976450780342994,
                    "error_high": 0.030976450780342994
                },
                {
                    "bin": [
                        0.18,
                        0.2
                    ],
                    "value": 0.01265978897487807,
                    "error_low": 0.01237133797594867,
                    "error_high": 0.01237133797594867
                },
                {
                    "bin": [
                        0.2,
                        0.22
                    ],
                    "value": 0.024342749581805097,
                    "error_low": 0.01166023584357225,
                    "error_high": 0.01166023584357225
                },
                {
                    "bin": [
                        0.22,
                        0.24
                    ],
                    "value": 0.0060175153580764055,
                    "error_low": 0.006153013448639282,
                    "error_high": 0.006153013448639282
                },
                {
                    "bin": [
                        0.24,
                        0.26
                    ],
                    "value": 0.0036215316540189574,
                    "error_low": 0.0063370481865852556,
                    "error_high": 0.0063370481865852556
                },
                {
                    "bin": [
                        0.26,
                        0.28
                    ],
                    "value": 0.009019793703165118,
                    "error_low": 0.005189371990472881,
                    "error_high": 0.005189371990472881
                },
                {
                    "bin": [
                        0.28,
                        0.3
                    ],
                    "value": 0.009554728951171904,
                    "error_low": 0.005487239325255981,
                    "error_high": 0.005487239325255981
                },
                {
                    "bin": [
                        0.3,
                        0.32
                    ],
                    "value": 0.0064318626306081265,
                    "error_low": 0.004710698831405475,
                    "error_high": 0.004710698831405475
                },
                {
                    "bin": [
                        0.32,
                        0.34
                    ],
                    "value": 0.011945681999645229,
                    "error_low": 0.006144177225890593,
                    "error_high": 0.006144177225890593
                },
                {
                    "bin": [
                        0.34,
                        0.36
                    ],
                    "value": 0.014817055045681244,
                    "error_low": 0.006428063543605952,
                    "error_high": 0.006428063543605952
                },
                {
                    "bin": [
                        0.36,
                        0.38
                    ],
                    "value": 0.008788477682876553,
                    "error_low": 0.006455459382030773,
                    "error_high": 0.006455459382030773
                },
                {
                    "bin": [
                        0.38,
                        0.4
                    ],
                    "value": 0.01845108263426647,
                    "error_low": 0.008923681582623558,
                    "error_high": 0.008923681582623558
                },
                {
                    "bin": [
                        0.4,
                        0.42
                    ],
                    "value": 0.015438602041094679,
                    "error_low": 0.007948425898111587,
                    "error_high": 0.007948425898111587
                },
                {
                    "bin": [
                        0.42,
                        0.44
                    ],
                    "value": 0.0027066805805900404,
                    "error_low": 0.006299414680959384,
                    "error_high": 0.006299414680959384
                },
                {
                    "bin": [
                        0.46,
                        0.48
                    ],
                    "value": 0.008416234591195249,
                    "error_low": 0.0076404481072017616,
                    "error_high": 0.0076404481072017616
                },
                {
                    "bin": [
                        0.48,
                        0.5
                    ],
                    "value": 0.016722566242810318,
                    "error_low": 0.011345416005584807,
                    "error_high": 0.011345416005584807
                },
                {
                    "bin": [
                        0.5,
                        0.52
                    ],
                    "value": 0.006726571565300552,
                    "error_low": 0.008290251198554088,
                    "error_high": 0.008290251198554088
                },
                {
                    "bin": [
                        0.52,
                        0.54
                    ],
                    "value": 0.0131215801164858,
                    "error_low": 0.014545376255719568,
                    "error_high": 0.014545376255719568
                },
                {
                    "bin": [
                        0.54,
                        0.56
                    ],
                    "value": 0.017578603925938185,
                    "error_low": 0.018570875278768648,
                    "error_high": 0.018570875278768648
                },
                {
                    "bin": [
                        0.56,
                        0.58
                    ],
                    "value": 0.053314764188222306,
                    "error_low": 0.031311881004001035,
                    "error_high": 0.031311881004001035
                },
                {
                    "bin": [
                        0.58,
                        0.6
                    ],
                    "value": 0.011494898126356146,
                    "error_low": 0.014171229803452545,
                    "error_high": 0.014171229803452545
                },
                {
                    "bin": [
                        0.6,
                        0.62
                    ],
                    "value": 0.029677869815258735,
                    "error_low": 0.024304143602417037,
                    "error_high": 0.024304143602417037
                },
                {
                    "bin": [
                        0.68,
                        0.7000000000000001
                    ],
                    "value": 0.12633898303187419,
                    "error_low": 0.1062228665501241,
                    "error_high": 0.1062228665501241
                },
                {
                    "bin": [
                        0.72,
                        0.74
                    ],
                    "value": 0.11950208108476978,
                    "error_low": 0.14252503539364567,
                    "error_high": 0.14252503539364567
                },
                {
                    "bin": [
                        0.74,
                        0.76
                    ],
                    "value": 0.50826898081142,
                    "error_low": 13.167724995493813,
                    "error_high": 13.167724995493813
                },
                {
                    "bin": [
                        0.88,
                        0.9
                    ],
                    "value": 9.089867553569343,
                    "error_low": 38.98018315980806,
                    "error_high": 38.98018315980806
                }
            ]
        }
    ]
}