{
    "dimension": 2,
    "variables": [
        "Eta",
        "Pt"
    ],
    "error_type": "absolute",
    "binning": {
        "x": [
            -2.5,
            2.5
        ],
        "y": [
            0.16,
            0.18,
            0.2,
            0.22,
            0.24,
            0.26,
            0.28,
            0.3,
            0.32,
            0.34,
            0.36,
            0.38,
            0.4,
            0.42,
            0.44,
            0.46,
            0.48,
            0.5,
            0.52,
            0.54,
            0.56,
            0.58,
            0.6,
            0.62,
            0.64,
            0.66,
            0.68,
            0.7000000000000001,
            0.72,
            0.74,
            0.76,
            0.78,
            0.8,
            0.8200000000000001,
            0.84,
            0.86,
            0.88,
            0.9,
            0.92,
            0.9400000000000001,
            0.96,
            0.98,
            1.0
        ]
    },
    "data": [
        {
            "bin": [
                -2.5,
                2.5
            ],
            "values": [
                {
                    "bin": [
                        0.16,
                        0.18
                    ],
                    "value": 0.09595356943453891,
                    "error_low": 0.0338368719976873,
                    "error_high": 0.0338368719976873
                },
                {
                    "bin": [
                        0.18,
                        0.2
                    ],
                    "value": 0.09373848610498126,
                    "error_low": 0.010254458284402699,
                    "error_high": 0.010254458284402699
                },
                {
                    "bin": [
                        0.2,
                        0.22
                    ],
                    "value": 0.11945983154002454,
                    "error_low": 0.006196049125459823,
                    "error_high": 0.006196049125459823
                },
                {
                    "bin": [
                        0.22,
                        0.24
                    ],
                    "value": 0.12207372940354747,
                    "error_low": 0.004624580371596092,
                    "error_high": 0.004624580371596092
                },
                {
                    "bin": [
                        0.24,
                        0.26
                    ],
                    "value": 0.11786249837779071,
                    "error_low": 0.003994481864133271,
                    "error_high": 0.003994481864133271
                },
                {
                    "bin": [
                        0.26,
                        0.28
                    ],
                    "value": 0.11758942836444669,
                    "error_low": 0.003692521302390635,
                    "error_high": 0.003692521302390635
                },
                {
                    "bin": [
                        0.28,
                        0.3
                    ],
                    "value": 0.12007116168737667,
                    "error_low": 0.003547140269335471,
                    "error_high": 0.003547140269335471
                },
                {
                    "bin": [
                        0.3,
                        0.32
                    ],
                    "value": 0.11599326010770088,
                    "error_low": 0.003509921270579096,
                    "error_high": 0.003509921270579096
                },
                {
                    "bin": [
                        0.32,
                        0.34
                    ],
                    "value": 0.1161922255886066,
                    "error_low": 0.003398279095221016,
                    "error_high": 0.003398279095221016
                },
                {
                    "bin": [
                        0.34,
                        0.36
                    ],
                    "value": 0.12236704548107079,
                    "error_low": 0.0034425718730951406,
                    "error_high": 0.0034425718730951406
                },
                {
                    "bin": [
                        0.36,
                        0.38
                    ],
                    "value": 0.11671627744673056,
                    "error_low": 0.0033969842114528986,
                    "error_high": 0.0033969842114528986
                },
                {
                    "bin": [
                        0.38,
                        0.4
                    ],
                    "value": 0.12147486653227738,
                    "error_low": 0.0034224529180066146,
                    "error_high": 0.0034224529180066146
                },
                {
                    "bin": [
                        0.4,
                        0.42
                    ],
                    "value": 0.11506667617273236,
                    "error_low": 0.003411148106332405,
                    "error_high": 0.003411148106332405
                },
                {
                    "bin": [
                        0.42,
                        0.44
                    ],
                    "value": 0.11580017844507359,
                    "error_low": 0.0033632279785342136,
                    "error_high": 0.0033632279785342136
                },
                {
                    "bin": [
                        0.44,
                        0.46
                    ],
                    "value": 0.11887721880900033,
                    "error_low": 0.00330332823590208,
                    "error_high": 0.00330332823590208
                },
                {
                    "bin": [
                        0.46,
                        0.48
                    ],
                    "value": 0.10955185026036576,
                    "error_low": 0.0031304528087701972,
                    "error_high": 0.0031304528087701972
                },
                {
                    "bin": [
                        0.48,
                        0.5
                    ],
                    "value": 0.11474841269742721,
                    "error_low": 0.0030708854263881624,
                    "error_high": 0.0030708854263881624
                },
                {
                    "bin": [
                        0.5,
                        0.52
                    ],
                    "value": 0.11923851088184471,
                    "error_low": 0.0029162848455073966,
                    "error_high": 0.0029162848455073966
                },
                {
                    "bin": [
                        0.52,
                        0.54
                    ],
                    "value": 0.11134184312172293,
                    "error_low": 0.0027915824614345125,
                    "error_high": 0.0027915824614345125
                },
                {
                    "bin": [
                        0.54,
                        0.56
                    ],
                    "value": 0.11661345574327488,
                    "error_low": 0.002777494222348205,
                    "error_high": 0.002777494222348205
                },
                {
                    "bin": [
                        0.56,
                        0.58
                    ],
                    "value": 0.1168713991557673,
                    "error_low": 0.002699999382479198,
                    "error_high": 0.002699999382479198
                },
                {
                    "bin": [
                        0.58,
                        0.6
                    ],
                    "value": 0.11915927165904978,
                    "error_low": 0.002676725645721692,
                    "error_high": 0.002676725645721692
                },
                {
                    "bin": [
                        0.6,
                        0.62
                    ],
                    "value": 0.1196962218707236,
                    "error_low": 0.002640301422088396,
                    "error_high": 0.002640301422088396
                },
                {
                    "bin": [
                        0.62,
                        0.64
                    ],
                    "value": 0.11948420402338006,
                    "error_low": 0.0025475744242672523,
                    "error_high": 0.0025475744242672523
                },
                {
                    "bin": [
                        0.64,
                        0.66
                    ],
                    "value": 0.11830731377981538,
                    "error_low": 0.0025475115390486925,
                    "error_high": 0.0025475115390486925
                },
                {
                    "bin": [
                        0.66,
                        0.68
                    ],
                    "value": 0.12523486962034386,
                    "error_low": 0.0025086150581378306,
                    "error_high": 0.0025086150581378306
                },
                {
                    "bin": [
                        0.68,
                        0.7000000000000001
                    ],
                    "value": 0.12242465751188024,
                    "error_low": 0.00248163503119812,
                    "error_high": 0.00248163503119812
                },
                {
                    "bin": [
                        0.7000000000000001,
                        0.72
                    ],
                    "value": 0.12226035375259936,
                    "error_low": 0.002481630272602397,
                    "error_high": 0.002481630272602397
                },
                {
                    "bin": [
                        0.72,
                        0.74
                    ],
                    "value": 0.12518658808216174,
                    "error_low": 0.002500437045141771,
                    "error_high": 0.002500437045141771
                },
                {
                    "bin": [
                        0.74,
                        0.76
                    ],
                    "value": 0.12275034341242629,
                    "error_low": 0.0025191194974742846,
                    "error_high": 0.0025191194974742846
                },
                {
                    "bin": [
                        0.76,
                        0.78
                    ],
                    "value": 0.12725472991901343,
                    "error_low": 0.002594315892785793,
                    "error_high": 0.002594315892785793
                },
                {
                    "bin": [
                        0.78,
                        0.8
                    ],
                    "value": 0.12975717680406307,
                    "error_low": 0.0027012674433082974,
                    "error_high": 0.0027012674433082974
                },
                {
                    "bin": [
                        0.8,
                        0.8200000000000001
                    ],
                    "value": 0.13148892499867793,
                    "error_low": 0.002869886160743546,
                    "error_high": 0.002869886160743546
                },
                {
                    "bin": [
                        0.8200000000000001,
                        0.84
                    ],
                    "value": 0.13760261922401065,
                    "error_low": 0.003071084958216607,
                    "error_high": 0.003071084958216607
                },
                {
                    "bin": [
                        0.84,
                        0.86
                    ],
                    "value": 0.13798343132171045,
                    "error_low": 0.0032718641402959803,
                    "error_high": 0.0032718641402959803
                },
                {
                    "bin": [
                        0.86,
                        0.88
                    ],
                    "value": 0.1492953788551183,
                    "error_low": 0.0037408534983136644,
                    "error_high": 0.0037408534983136644
                },
                {
                    "bin": [
                        0.88,
                        0.9
                    ],
                    "value": 0.15418647843205038,
                    "error_low": 0.004490108275160978,
                    "error_high": 0.004490108275160978
                },
                {
                    "bin": [
                        0.9,
                        0.92
                    ],
                    "value": 0.15358467763615957,
                    "error_low": 0.005550745143078504,
                    "error_high": 0.005550745143078504
                },
                {
                    "bin": [
                        0.92,
                        0.9400000000000001
                    ],
                    "value": 0.15599583665580075,
                    "error_low": 0.007626856373519852,
                    "error_high": 0.007626856373519852
                },
                {
                    "bin": [
                        0.9400000000000001,
                        0.96
                    ],
                    "value": 0.17643926773356103,
                    "error_low": 0.012787435262560511,
                    "error_high": 0.012787435262560511
                },
                {
                    "bin": [
                        0.96,
                        0.98
                    ],
                    "value": 0.23939376248765254,
                    "error_low": 0.02948081437085512,
                    "error_high": 0.02948081437085512
                },
                {
                    "bin": [
                        0.98,
                        1.0
                    ],
                    "value": 0.1640400468104158,
                    "error_low": 0.07633255523551818,
                    "error_high": 0.07633255523551818
                }
            ]
        }
    ]
}