{
    "dimension": 2,
    "variables": [
        "Eta",
        "Pt"
    ],
    "error_type": "absolute",
    "binning": {
        "x": [
            -2.5,
            2.5
        ],
        "y": [
            30.0,
            40.0,
            50.0,
            60.0,
            70.0,
            80.0,
            90.0,
            100.0,
            120.0,
            160.0,
            200.0
        ]
    },
    "data": [
        {
            "bin": [
                -2.5,
                2.5
            ],
            "values": [
                {
                    "bin": [
                        30.0,
                        40.0
                    ],
                    "value": 0.08650531411208917,
                    "error_low": 0.0036764454519942866,
                    "error_high": 0.0036764454519942866
                },
                {
                    "bin": [
                        40.0,
                        50.0
                    ],
                    "value": 0.08531957422794541,
                    "error_low": 0.003992080246635947,
                    "error_high": 0.003992080246635947
                },
                {
                    "bin": [
                        50.0,
                        60.0
                    ],
                    "value": 0.09179216263459986,
                    "error_low": 0.004290003996542991,
                    "error_high": 0.004290003996542991
                },
                {
                    "bin": [
                        60.0,
                        70.0
                    ],
                    "value": 0.10397055841478069,
                    "error_low": 0.004879725459612203,
                    "error_high": 0.004879725459612203
                },
                {
                    "bin": [
                        70.0,
                        80.0
                    ],
                    "value": 0.10761571247301592,
                    "error_low": 0.005687374854203055,
                    "error_high": 0.005687374854203055
                },
                {
                    "bin": [
                        80.0,
                        90.0
                    ],
                    "value": 0.11474459176479994,
                    "error_low": 0.006732278679026653,
                    "error_high": 0.006732278679026653
                },
                {
                    "bin": [
                        90.0,
                        100.0
                    ],
                    "value": 0.11503812351719904,
                    "error_low": 0.008080992181598828,
                    "error_high": 0.008080992181598828
                },
                {
                    "bin": [
                        100.0,
                        120.0
                    ],
                    "value": 0.12960067885066096,
                    "error_low": 0.007981862798723564,
                    "error_high": 0.007981862798723564
                },
                {
                    "bin": [
                        120.0,
                        160.0
                    ],
                    "value": 0.13559153796745238,
                    "error_low": 0.010584939977938463,
                    "error_high": 0.010584939977938463
                },
                {
                    "bin": [
                        160.0,
                        200.0
                    ],
                    "value": 0.11923422627003563,
                    "error_low": 0.020056129500924835,
                    "error_high": 0.020056129500924835
                }
            ]
        }
    ]
}