{
    "dimension": 2,
    "variables": [
        "Eta",
        "Pt"
    ],
    "error_type": "absolute",
    "binning": {
        "x": [
            -2.5,
            2.5
        ],
        "y": [
            200.0,
            220.0,
            240.0,
            260.0,
            280.0,
            300.0,
            350.0,
            400.0,
            500.0,
            600.0
        ]
    },
    "data": [
        {
            "bin": [
                -2.5,
                2.5
            ],
            "values": [
                {
                    "bin": [
                        200.0,
                        220.0
                    ],
                    "value": 0.07129188736057543,
                    "error_low": 0.009139997955450091,
                    "error_high": 0.009139997955450091
                },
                {
                    "bin": [
                        220.0,
                        240.0
                    ],
                    "value": 0.06849756480342958,
                    "error_low": 0.009602073132968117,
                    "error_high": 0.009602073132968117
                },
                {
                    "bin": [
                        240.0,
                        260.0
                    ],
                    "value": 0.06183940782167775,
                    "error_low": 0.010505389556614087,
                    "error_high": 0.010505389556614087
                },
                {
                    "bin": [
                        260.0,
                        280.0
                    ],
                    "value": 0.08036416489094936,
                    "error_low": 0.013950964933937523,
                    "error_high": 0.013950964933937523
                },
                {
                    "bin": [
                        280.0,
                        300.0
                    ],
                    "value": 0.08266724582880246,
                    "error_low": 0.014325052731060222,
                    "error_high": 0.014325052731060222
                },
                {
                    "bin": [
                        300.0,
                        350.0
                    ],
                    "value": 0.0785384690209238,
                    "error_low": 0.012212569308901628,
                    "error_high": 0.012212569308901628
                },
                {
                    "bin": [
                        350.0,
                        400.0
                    ],
                    "value": 0.0996526177363912,
                    "error_low": 0.018354441601627816,
                    "error_high": 0.018354441601627816
                },
                {
                    "bin": [
                        400.0,
                        500.0
                    ],
                    "value": 0.10880915179702849,
                    "error_low": 0.02076856787241445,
                    "error_high": 0.02076856787241445
                },
                {
                    "bin": [
                        500.0,
                        600.0
                    ],
                    "value": 0.1255872862337544,
                    "error_low": 0.042704406943645364,
                    "error_high": 0.042704406943645364
                }
            ]
        }
    ]
}